printpgm/__init__.py
printpgm/texts.py
printpkg/__init__.py
printpkg/texts.py
printpgm-0.3.dist-info/METADATA
printpgm-0.3.dist-info/WHEEL
printpgm-0.3.dist-info/top_level.txt
printpgm-0.3.dist-info/RECORD
