Metadata-Version: 2.4
Name: printpgm
Version: 0.3
Summary: A simple package to print predefined texts
Author: forgiveme
Author-email: plshelpme.email@example.com
Requires-Dist: pyperclip>=1.8.0
Dynamic: author
Dynamic: author-email
Dynamic: requires-dist
Dynamic: summary
